burp_ui-1.1.1.data/data/share/burpui/contrib/centos/init.sh
burp_ui-1.1.1.data/data/share/burpui/contrib/freebsd/gunicorn.rc
burp_ui-1.1.1.data/data/share/burpui/contrib/gunicorn/burpui_gunicorn.py
burp_ui-1.1.1.data/data/share/burpui/contrib/systemd/bui-agent.service
burp_ui-1.1.1.data/data/share/burpui/contrib/systemd/bui-celery-beat.service
burp_ui-1.1.1.data/data/share/burpui/contrib/systemd/bui-celery.service
burp_ui-1.1.1.data/data/share/burpui/contrib/systemd/bui-gunicorn.service
burp_ui-1.1.1.data/data/share/burpui/contrib/systemd/bui-monitor.service
burp_ui-1.1.1.data/data/share/burpui/contrib/systemd/bui-websocket.service
burp_ui-1.1.1.data/data/share/burpui/etc/burpui.sample.cfg
burp_ui-1.1.1.data/data/share/burpui/migrations/README
burp_ui-1.1.1.data/data/share/burpui/migrations/alembic.ini
burp_ui-1.1.1.data/data/share/burpui/migrations/env.py
burp_ui-1.1.1.data/data/share/burpui/migrations/script.py.mako
burp_ui-1.1.1.data/data/share/burpui/migrations/versions/225d9b2f0fb1_initial.py
burp_ui-1.1.1.data/data/share/burpui/migrations/versions/4445080944ee_hidden_hosts_management.py
burp_ui-1.1.1.data/data/share/burpui/migrations/versions/56de018f4d88_user_prefs.py
burp_ui-1.1.1.data/data/share/burpui/migrations/versions/695dcbd29d4f_increase_pref_value_size.py
burp_ui-1.1.1.data/data/share/burpui/migrations/versions/7f317474332d_handle_sessions.py
burp_ui-1.1.1.data/data/share/burpui/migrations/versions/fc07e3fa0086_sql_compatibility.py
burpui/RELEASE
burpui/VERSION
burpui/__init__.py
burpui/__main__.py
burpui/_cli.py
burpui/_compat.py
burpui/_json.py
burpui/_rtfd.py
burpui/app.py
burpui/celerybeat-schedule
burpui/cli.py
burpui/config.py
burpui/datastructures.py
burpui/decorators.py
burpui/desc.py
burpui/exceptions.py
burpui/extensions.py
burpui/filter.py
burpui/forms.py
burpui/models.py
burpui/plugins.py
burpui/routes.py
burpui/security.py
burpui/sessions.py
burpui/tasks.py
burpui/utils.py
burpui/.ropeproject/config.py
burpui/.ropeproject/globalnames
burp_ui-1.1.1.dist-info/LICENSE
burp_ui-1.1.1.dist-info/METADATA
burp_ui-1.1.1.dist-info/WHEEL
burp_ui-1.1.1.dist-info/entry_points.txt
burp_ui-1.1.1.dist-info/top_level.txt
burp_ui-1.1.1.dist-info/RECORD
