Metadata-Version: 2.1
Name: burp-ui
Version: 1.1.1
Summary: Burp-UI is a web-ui for burp backup written in python with Flask and jQuery/Bootstrap
Home-page: https://git.ziirish.me/ziirish/burp-ui
Author: Benjamin SANS (Ziirish)
Author-email: hi+burpui@ziirish.me
License: BSD 3-clause License
Keywords: burp web ui backup monitoring
Platform: UNKNOWN
Classifier: Framework :: Flask
Classifier: Intended Audience :: System Administrators
Classifier: Natural Language :: English
Classifier: License :: OSI Approved :: BSD License
Classifier: Operating System :: POSIX :: Linux
Classifier: Programming Language :: Python
Classifier: Programming Language :: Python :: 3
Classifier: Topic :: System :: Archiving :: Backup
Classifier: Topic :: System :: Monitoring
Requires-Python: >=3.7
License-File: LICENSE
Requires-Dist: trio (==0.22.0)
Requires-Dist: Flask (==2.2.3)
Requires-Dist: Flask-Login (==0.6.2)
Requires-Dist: Flask-Babel (==3.0.1)
Requires-Dist: Flask-WTF (==0.15.1)
Requires-Dist: flask-restx (==1.1.0)
Requires-Dist: Flask-Caching (==2.0.2)
Requires-Dist: Flask-Session (==0.4.0)
Requires-Dist: WTForms (==3.0.0)
Requires-Dist: arrow (==1.2.3)
Requires-Dist: pluginbase (==1.0.1)
Requires-Dist: tzlocal (==4.3)
Requires-Dist: pyOpenSSL (==23.0.0)
Requires-Dist: configobj (==5.0.8)
Requires-Dist: async-generator (==1.10)
Requires-Dist: Click (==8.1.3)
Requires-Dist: python-pam (==2.0.2)
Provides-Extra: celery
Requires-Dist: Celery (>=4.3) ; extra == 'celery'
Requires-Dist: redis ; extra == 'celery'
Provides-Extra: ci
Requires-Dist: pytest ; extra == 'ci'
Requires-Dist: pytest-cov ; extra == 'ci'
Requires-Dist: pytest-flask ; extra == 'ci'
Requires-Dist: pytest-mock ; extra == 'ci'
Requires-Dist: nose ; extra == 'ci'
Requires-Dist: coverage ; extra == 'ci'
Requires-Dist: mock ; extra == 'ci'
Requires-Dist: mockredispy ; extra == 'ci'
Requires-Dist: Flask-Session ; extra == 'ci'
Requires-Dist: Celery ; extra == 'ci'
Requires-Dist: redis ; extra == 'ci'
Requires-Dist: Flask-SQLAlchemy ; extra == 'ci'
Requires-Dist: Flask-Migrate ; extra == 'ci'
Requires-Dist: sqlalchemy-utils ; extra == 'ci'
Provides-Extra: dev
Requires-Dist: flake8 ; extra == 'dev'
Requires-Dist: pylint ; extra == 'dev'
Requires-Dist: black ; extra == 'dev'
Provides-Extra: gunicorn
Requires-Dist: gunicorn ; extra == 'gunicorn'
Provides-Extra: gunicorn-extra
Requires-Dist: redis ; extra == 'gunicorn-extra'
Provides-Extra: ldap_authentication
Requires-Dist: ldap3 ; extra == 'ldap_authentication'
Provides-Extra: limit
Requires-Dist: Flask-Limiter ; extra == 'limit'
Requires-Dist: redis ; extra == 'limit'
Provides-Extra: rtd
Requires-Dist: sphinxcontrib-httpdomain (==1.8.0) ; extra == 'rtd'
Provides-Extra: sql
Requires-Dist: Flask-SQLAlchemy ; extra == 'sql'
Requires-Dist: Flask-Migrate (>=2.1.0) ; extra == 'sql'
Requires-Dist: sqlalchemy-utils ; extra == 'sql'
Provides-Extra: websocket
Requires-Dist: flask-socketio ; extra == 'websocket'
Requires-Dist: redis ; extra == 'websocket'
Requires-Dist: gevent-websocket ; extra == 'websocket'
